odoo9_addon_mass_mailing_custom_unsubscribe-9.0.3.0.0-py2.7-nspkg.pth
odoo9_addon_mass_mailing_custom_unsubscribe-9.0.3.0.0.dist-info/DESCRIPTION.rst
odoo9_addon_mass_mailing_custom_unsubscribe-9.0.3.0.0.dist-info/METADATA
odoo9_addon_mass_mailing_custom_unsubscribe-9.0.3.0.0.dist-info/RECORD
odoo9_addon_mass_mailing_custom_unsubscribe-9.0.3.0.0.dist-info/WHEEL
odoo9_addon_mass_mailing_custom_unsubscribe-9.0.3.0.0.dist-info/metadata.json
odoo9_addon_mass_mailing_custom_unsubscribe-9.0.3.0.0.dist-info/namespace_packages.txt
odoo9_addon_mass_mailing_custom_unsubscribe-9.0.3.0.0.dist-info/top_level.txt
odoo_addons/mass_mailing_custom_unsubscribe/README.rst
odoo_addons/mass_mailing_custom_unsubscribe/__init__.py
odoo_addons/mass_mailing_custom_unsubscribe/__openerp__.py
odoo_addons/mass_mailing_custom_unsubscribe/exceptions.py
odoo_addons/mass_mailing_custom_unsubscribe/controllers/__init__.py
odoo_addons/mass_mailing_custom_unsubscribe/controllers/main.py
odoo_addons/mass_mailing_custom_unsubscribe/data/mail_unsubscription_reason.xml
odoo_addons/mass_mailing_custom_unsubscribe/demo/assets.xml
odoo_addons/mass_mailing_custom_unsubscribe/i18n/am.po
odoo_addons/mass_mailing_custom_unsubscribe/i18n/ar.po
odoo_addons/mass_mailing_custom_unsubscribe/i18n/bg.po
odoo_addons/mass_mailing_custom_unsubscribe/i18n/bs.po
odoo_addons/mass_mailing_custom_unsubscribe/i18n/ca.po
odoo_addons/mass_mailing_custom_unsubscribe/i18n/ca_ES.po
odoo_addons/mass_mailing_custom_unsubscribe/i18n/cs.po
odoo_addons/mass_mailing_custom_unsubscribe/i18n/da.po
odoo_addons/mass_mailing_custom_unsubscribe/i18n/da_DK.po
odoo_addons/mass_mailing_custom_unsubscribe/i18n/de.po
odoo_addons/mass_mailing_custom_unsubscribe/i18n/el_GR.po
odoo_addons/mass_mailing_custom_unsubscribe/i18n/en_GB.po
odoo_addons/mass_mailing_custom_unsubscribe/i18n/es.po
odoo_addons/mass_mailing_custom_unsubscribe/i18n/es_AR.po
odoo_addons/mass_mailing_custom_unsubscribe/i18n/es_CL.po
odoo_addons/mass_mailing_custom_unsubscribe/i18n/es_CO.po
odoo_addons/mass_mailing_custom_unsubscribe/i18n/es_CR.po
odoo_addons/mass_mailing_custom_unsubscribe/i18n/es_DO.po
odoo_addons/mass_mailing_custom_unsubscribe/i18n/es_EC.po
odoo_addons/mass_mailing_custom_unsubscribe/i18n/es_ES.po
odoo_addons/mass_mailing_custom_unsubscribe/i18n/es_MX.po
odoo_addons/mass_mailing_custom_unsubscribe/i18n/es_PE.po
odoo_addons/mass_mailing_custom_unsubscribe/i18n/es_PY.po
odoo_addons/mass_mailing_custom_unsubscribe/i18n/es_VE.po
