Metadata-Version: 2.0
Name: odoo9-addon-mass-mailing-custom-unsubscribe
Version: 9.0.3.0.0
Summary: Know and track (un)subscription reasons, GDPR compliant
Home-page: https://www.tecnativa.com
Author: Antiun Ingeniería S.L., Tecnativa,Odoo Community Association (OCA)
Author-email: support@odoo-community.org
License: AGPL-3
Platform: UNKNOWN
Classifier: Programming Language :: Python
Classifier: Framework :: Odoo
Classifier: License :: OSI Approved :: GNU Affero General Public License v3
Requires-Python: ~=2.7
Requires-Dist: odoo (<9.1a,>=9.0a)
